amplify_sched/__init__.py
amplify_sched/amplify_sched.py
amplify_sched-0.2.2.dist-info/licenses/LICENSE
amplify_sched-0.2.2.dist-info/METADATA
amplify_sched-0.2.2.dist-info/WHEEL
amplify_sched-0.2.2.dist-info/top_level.txt
amplify_sched-0.2.2.dist-info/RECORD
